<plominodatabase id="iol_base">
  <design>
    <element id="base_com_protocollo" title="Inserimento dati di protocollo" type="PlominoForm">
      <id type="Products.Archetypes.Field.StringField">base_com_protocollo</id>
      <onCreateDocument type="Products.Archetypes.Field.TextField"><![CDATA[]]></onCreateDocument>
      <onOpenDocument type="Products.Archetypes.Field.TextField"><![CDATA[context.frm_onOpenDocument()]]></onOpenDocument>
      <beforeSaveDocument type="Products.Archetypes.Field.TextField"><![CDATA[]]></beforeSaveDocument>
      <onSaveDocument type="Products.Archetypes.Field.TextField"><![CDATA[context.frm_onSaveDocument()]]></onSaveDocument>
      <onDeleteDocument type="Products.Archetypes.Field.TextField"><![CDATA[]]></onDeleteDocument>
      <onSearch type="Products.Archetypes.Field.TextField"><![CDATA[]]></onSearch>
      <beforeCreateDocument type="Products.Archetypes.Field.TextField"><![CDATA[]]></beforeCreateDocument>
      <FormLayout type="Products.Archetypes.Field.TextField"><![CDATA[<div class="v-content well"><div class="row-fluid"><div class="span3"><span class="plominoFieldClass">numero_protocollo</span></div><div class="span3"><span class="plominoFieldClass">data_protocollo</span></div></div></div><div class="hidden" id="btn-group"><span class="plominoActionClass">btn_salva</span> <span class="plominoActionClass">btn_annulla</span></div>]]></FormLayout>
      <DocumentTitle type="Products.Archetypes.Field.TextField"><![CDATA[]]></DocumentTitle>
      <DocumentId type="Products.Archetypes.Field.TextField"><![CDATA[]]></DocumentId>
      <ActionBarPosition type="Products.Archetypes.Field.StringField">TOP</ActionBarPosition>
      <HideDefaultActions type="Products.Archetypes.Field.BooleanField">True</HideDefaultActions>
      <HideInMenu type="Products.Archetypes.Field.BooleanField">True</HideInMenu>
      <isSearchForm type="Products.Archetypes.Field.BooleanField">False</isSearchForm>
      <isPage type="Products.Archetypes.Field.BooleanField">False</isPage>
      <SearchView type="Products.Archetypes.Field.StringField"/>
      <SearchFormula type="Products.Archetypes.Field.TextField"><![CDATA[]]></SearchFormula>
      <Position type="Products.Archetypes.Field.IntegerField"/>
      <excludeFromNav type="Products.Archetypes.Field.BooleanField">False</excludeFromNav>
      <elements>
        <element id="numero_protocollo" title="Protocollo" type="PlominoField">
          <id type="Products.Archetypes.Field.StringField">numero_protocollo</id>
          <FieldType type="Products.Archetypes.Field.StringField">TEXT</FieldType>
          <FieldMode type="Products.Archetypes.Field.StringField">EDITABLE</FieldMode>
          <Formula type="Products.Archetypes.Field.TextField"><![CDATA[]]></Formula>
          <FieldReadTemplate type="Products.Archetypes.Field.StringField">bootstrapTextRead</FieldReadTemplate>
          <FieldEditTemplate type="Products.Archetypes.Field.StringField">bootstrapTextEdit</FieldEditTemplate>
          <Mandatory type="Products.Archetypes.Field.BooleanField">False</Mandatory>
          <ValidationFormula type="Products.Archetypes.Field.TextField"><![CDATA[]]></ValidationFormula>
          <ToBeIndexed type="Products.Archetypes.Field.BooleanField">False</ToBeIndexed>
          <IndexType type="Products.Archetypes.Field.StringField">DEFAULT</IndexType>
          <CustomData>
            <extensionfields ExportImportClass="Products.CMFPlomino.tests.schemaextender.importexport.ExtendedFieldImportExporter">
              <field name="fieldDescription"/>
              <field name="customAttributes"/>
            </extensionfields>
          </CustomData>
        </element>
        <element id="btn_salva" title="Salva" type="PlominoAction">
          <id type="Products.Archetypes.Field.StringField">btn_salva</id>
          <ActionType type="Products.Archetypes.Field.StringField">SAVE</ActionType>
          <ActionDisplay type="Products.Archetypes.Field.StringField">SUBMIT</ActionDisplay>
          <Content type="Products.Archetypes.Field.TextField"><![CDATA[]]></Content>
          <Hidewhen type="Products.Archetypes.Field.TextField"><![CDATA[not context.isEditMode()]]></Hidewhen>
          <InActionBar type="Products.Archetypes.Field.BooleanField">False</InActionBar>
        </element>
        <element id="btn_annulla" title="Annulla" type="PlominoAction">
          <id type="Products.Archetypes.Field.StringField">btn_annulla</id>
          <ActionType type="Products.Archetypes.Field.StringField">REDIRECT</ActionType>
          <ActionDisplay type="Products.Archetypes.Field.StringField">BUTTON</ActionDisplay>
          <Content type="Products.Archetypes.Field.TextField"><![CDATA[if context.isNewDocument():
    url=context.getParentDatabase().absolute_url()
else:
    url=context.absolute_url()
return '%s' %url]]></Content>
          <Hidewhen type="Products.Archetypes.Field.TextField"><![CDATA[not context.isEditMode()]]></Hidewhen>
          <InActionBar type="Products.Archetypes.Field.BooleanField">False</InActionBar>
        </element>
        <element id="data_protocollo" title="Data protocollo" type="PlominoField">
          <id type="Products.Archetypes.Field.StringField">data_protocollo</id>
          <FieldType type="Products.Archetypes.Field.StringField">DATE</FieldType>
          <FieldMode type="Products.Archetypes.Field.StringField">EDITABLE</FieldMode>
          <Formula type="Products.Archetypes.Field.TextField"><![CDATA[]]></Formula>
          <FieldReadTemplate type="Products.Archetypes.Field.StringField">bootstrapDateRead</FieldReadTemplate>
          <FieldEditTemplate type="Products.Archetypes.Field.StringField">bootstrapDatePicker</FieldEditTemplate>
          <Mandatory type="Products.Archetypes.Field.BooleanField">False</Mandatory>
          <ValidationFormula type="Products.Archetypes.Field.TextField"><![CDATA[]]></ValidationFormula>
          <ToBeIndexed type="Products.Archetypes.Field.BooleanField">True</ToBeIndexed>
          <IndexType type="Products.Archetypes.Field.StringField">DateIndex</IndexType>
          <params>
<param>
<value><struct>
<member>
<name>format</name>
<value><string>%d/%m/%Y</string></value>
</member>
<member>
<name>startingyear</name>
<value><string>1950</string></value>
</member>
</struct></value>
</param>
</params>
          <CustomData>
            <extensionfields ExportImportClass="Products.CMFPlomino.tests.schemaextender.importexport.ExtendedFieldImportExporter">
              <field name="fieldDescription"/>
              <field name="customAttributes">data-plugin="datepicker" data-datepicker-options="{changeMonth:true,changeYear: true,dateFormat:'dd/mm/yy'}"</field>
            </extensionfields>
          </CustomData>
        </element>
      </elements>
    </element>
  </design>
</plominodatabase>
